biobb_analysis/__init__.py
biobb_analysis/py.typed
biobb_analysis/ambertools/__init__.py
biobb_analysis/ambertools/common.py
biobb_analysis/ambertools/cpptraj_average.py
biobb_analysis/ambertools/cpptraj_bfactor.py
biobb_analysis/ambertools/cpptraj_convert.py
biobb_analysis/ambertools/cpptraj_dry.py
biobb_analysis/ambertools/cpptraj_image.py
biobb_analysis/ambertools/cpptraj_input.py
biobb_analysis/ambertools/cpptraj_mask.py
biobb_analysis/ambertools/cpptraj_rgyr.py
biobb_analysis/ambertools/cpptraj_rms.py
biobb_analysis/ambertools/cpptraj_rmsf.py
biobb_analysis/ambertools/cpptraj_slice.py
biobb_analysis/ambertools/cpptraj_snapshot.py
biobb_analysis/ambertools/cpptraj_strip.py
biobb_analysis/gromacs/__init__.py
biobb_analysis/gromacs/common.py
biobb_analysis/gromacs/gmx_check.py
biobb_analysis/gromacs/gmx_cluster.py
biobb_analysis/gromacs/gmx_energy.py
biobb_analysis/gromacs/gmx_image.py
biobb_analysis/gromacs/gmx_rgyr.py
biobb_analysis/gromacs/gmx_rms.py
biobb_analysis/gromacs/gmx_rmsf.py
biobb_analysis/gromacs/gmx_trjconv_str.py
biobb_analysis/gromacs/gmx_trjconv_str_ens.py
biobb_analysis/gromacs/gmx_trjconv_trj.py
biobb_analysis/test/__init__.py
biobb_analysis-5.2.0.dist-info/licenses/LICENSE
biobb_analysis-5.2.0.dist-info/METADATA
biobb_analysis-5.2.0.dist-info/WHEEL
biobb_analysis-5.2.0.dist-info/entry_points.txt
biobb_analysis-5.2.0.dist-info/top_level.txt
biobb_analysis-5.2.0.dist-info/RECORD
